do_py/__init__.py
do_py/abc/__init__.py
do_py/abc/constants.py
do_py/abc/messages.py
do_py/abc/utils.py
do_py/common/__init__.py
do_py/common/managed_datetime.py
do_py/common/managed_list.py
do_py/data_object/__init__.py
do_py/data_object/dynamic_restrictions.py
do_py/data_object/restricted_dict.py
do_py/data_object/restriction.py
do_py/data_object/validator.py
do_py/exceptions/__init__.py
do_py/exceptions/data_object_error.py
do_py/exceptions/restriction_error.py
do_py/utils/__init__.py
do_py/utils/json_encoder.py
do_py/utils/properties.py
do_py-0.4.1.dist-info/LICENSE
do_py-0.4.1.dist-info/METADATA
do_py-0.4.1.dist-info/WHEEL
do_py-0.4.1.dist-info/top_level.txt
do_py-0.4.1.dist-info/RECORD
