Metadata-Version: 2.1
Name: do-py
Version: 0.4.1
Summary: Data validation and standardization library wrapping Python dictionaries.
Home-page: https://github.com/do-py-together/do-py
Author: Tim Davis
Author-email: timdavis.3991@gmail.com
License: UNKNOWN
Keywords: development,OO
Platform: UNKNOWN
Classifier: Development Status :: 4 - Beta
Classifier: Intended Audience :: Developers
Classifier: Topic :: Software Development :: Build Tools
Classifier: Operating System :: OS Independent
Classifier: License :: OSI Approved :: MIT License
Classifier: Programming Language :: Python
Classifier: Programming Language :: Python :: 2
Classifier: Programming Language :: Python :: 2.7
Classifier: Programming Language :: Python :: 3.7
Classifier: Programming Language :: Python :: 3.8
Classifier: Programming Language :: Python :: 3.9
License-File: LICENSE
Requires-Dist: future (>=0.18)
